yummy_sphinx_theme/__init__.py
yummy_sphinx_theme/disqus-comments.html
yummy_sphinx_theme/layout.html
yummy_sphinx_theme/sourcelink.html
yummy_sphinx_theme/theme.conf
yummy_sphinx_theme/versions.html
yummy_sphinx_theme/static/css/bootstrap.css
yummy_sphinx_theme/static/css/bootstrap.min.css
yummy_sphinx_theme/static/css/font-awesome.css
yummy_sphinx_theme/static/css/font-awesome.min.css
yummy_sphinx_theme/static/css/hover-min.css
yummy_sphinx_theme/static/css/old.css
yummy_sphinx_theme/static/css/syntax.css
yummy_sphinx_theme/static/css/theme.css_t
yummy_sphinx_theme/static/fonts/FontAwesome.otf
yummy_sphinx_theme/static/fonts/fontawesome-webfont.eot
yummy_sphinx_theme/static/fonts/fontawesome-webfont.svg
yummy_sphinx_theme/static/fonts/fontawesome-webfont.ttf
yummy_sphinx_theme/static/fonts/fontawesome-webfont.woff
yummy_sphinx_theme/static/fonts/fontawesome-webfont.woff2
yummy_sphinx_theme/static/fonts/glyphicons-halflings-regular.eot
yummy_sphinx_theme/static/fonts/glyphicons-halflings-regular.svg
yummy_sphinx_theme/static/fonts/glyphicons-halflings-regular.ttf
yummy_sphinx_theme/static/fonts/glyphicons-halflings-regular.woff
yummy_sphinx_theme/static/fonts/glyphicons-halflings-regular.woff2
yummy_sphinx_theme/static/js/bootstrap.js
yummy_sphinx_theme/static/js/bootstrap.min.js
yummy_sphinx_theme/static/js/geopattern.min.js
yummy_sphinx_theme/static/js/jquery.js
yummy_sphinx_theme/static/js/jquery.min.js
yummy_sphinx_theme/static/js/jquery.slim.js
yummy_sphinx_theme/static/js/jquery.slim.min.js
yummy_sphinx_theme/static/js/script.js
yummy_sphinx_theme/static/js/theme.js
yummy_sphinx_theme/static/js/underscore-min.js
yummy_sphinx_theme/static/js/underscore.js
yummy_sphinx_theme-0.1.1.dist-info/DESCRIPTION.rst
yummy_sphinx_theme-0.1.1.dist-info/METADATA
yummy_sphinx_theme-0.1.1.dist-info/RECORD
yummy_sphinx_theme-0.1.1.dist-info/WHEEL
yummy_sphinx_theme-0.1.1.dist-info/entry_points.txt
yummy_sphinx_theme-0.1.1.dist-info/metadata.json
yummy_sphinx_theme-0.1.1.dist-info/top_level.txt
