Metadata-Version: 2.0
Name: yummy-sphinx-theme
Version: 0.1.1
Summary: A sphinx theme created to mirror Yummy-Jekyll
Home-page: https://github.com/TagnumElite/yummy_sphinx_theme
Author: Tagan Hoyle
Author-email: tagnum.elite@gmail.com
License: MIT
Platform: UNKNOWN
Classifier: Development Status :: 3 - Alpha
Classifier: Framework :: Sphinx
Classifier: Framework :: Sphinx :: Theme
Classifier: Intended Audience :: Developers
Classifier: License :: OSI Approved :: Apache Software License
Classifier: Operating System :: OS Independent
Classifier: Topic :: Documentation
Classifier: Topic :: Software Development :: Documentation
Classifier: Programming Language :: Python
Classifier: Programming Language :: Python :: 2.7
Classifier: Programming Language :: Python :: 3.4
Classifier: Programming Language :: Python :: 3.5
Classifier: Programming Language :: Python :: 3.6
